fastserve/__init__.py
fastserve/core.py
fastserve-0.1.0.dist-info/METADATA
fastserve-0.1.0.dist-info/WHEEL
fastserve-0.1.0.dist-info/licenses/LICENSE
fastserve-0.1.0.dist-info/RECORD
