Metadata-Version: 2.1
Name: fastserve
Version: 0.1.0
Summary: Add your description here
Author: Yasushi Itoh
License-File: LICENSE
Requires-Python: >=3.8
Requires-Dist: grpcio-health-checking>=1.56.2
Requires-Dist: grpcio-reflection>=1.56.2
Requires-Dist: grpcio-tools>=1.56.2
Requires-Dist: pydantic>=2.1.1
